pypact/__init__.py
pypact/pact.py
pypact/tools.py
pypact/utils.py
pypact_lang-0.3.5.dist-info/METADATA
pypact_lang-0.3.5.dist-info/WHEEL
pypact_lang-0.3.5.dist-info/top_level.txt
pypact_lang-0.3.5.dist-info/RECORD
