Metadata-Version: 2.1
Name: pypact-lang
Version: 0.3.5
Home-page: https://github.com/cyberfly-io/pypact
Requires-Dist: requests
Requires-Dist: pynacl
